jotpad/__init__.py
jotpad/cli.py
jotpad/config.py
jotpad-0.0.7.dist-info/METADATA
jotpad-0.0.7.dist-info/WHEEL
jotpad-0.0.7.dist-info/entry_points.txt
jotpad-0.0.7.dist-info/top_level.txt
jotpad-0.0.7.dist-info/RECORD
