Metadata-Version: 2.1
Name: jotpad
Version: 0.0.7
Summary: Jotpad is a cli tool for managing notes
Home-page: https://github.com/scrussell24/jotpad
Author: Scott Russell
Author-email: me@scottrussell.net
License: UNKNOWN
Platform: UNKNOWN
Classifier: Programming Language :: Python :: 3
Classifier: License :: OSI Approved :: MIT License
Classifier: Operating System :: OS Independent
Requires-Python: >=3.6
Requires-Dist: appdirs (>=1.4.0)
Requires-Dist: typer[all] (>=0.6.0)
